[
  {
    "segmentnr":"BO_T02_D1603:126b-0",
    "original":"@126b # \/\/ rgya gar skad du \/",
    "folio":"126b",
    "stemmed":"rgya gar skad du "
  },
  {
    "segmentnr":"BO_T02_D1603:126b-1",
    "original":"kra ma da yi badzra b'a r'a h'i sto tram \/",
    "folio":"126b",
    "stemmed":"kra ma da yi badzra ba ra h sto tram "
  },
  {
    "segmentnr":"BO_T02_D1603:126b-2",
    "original":"bod skad du \/",
    "folio":"126b",
    "stemmed":"bod skad du "
  },
  {
    "segmentnr":"BO_T02_D1603:126b-3",
    "original":"rdo rje phag mo'i bstod pa rim pa gnyis pa \/",
    "folio":"126b",
    "stemmed":"rdo rje phag mo bstod ba rim ba gnyis ba "
  },
  {
    "segmentnr":"BO_T02_D1603:126b-4",
    "original":"rdo rje btsun mo la phyag 'tshal lo \/\/",
    "folio":"126b",
    "stemmed":"rdo rje btsun mo la phyag tshal lo "
  },
  {
    "segmentnr":"BO_T02_D1603:126b-5",
    "original":"he ru ka dpal mchog tu rab dgyes pa'i \/\/",
    "folio":"126b",
    "stemmed":"he ru ka dpal mchog tu rab dgyes ba "
  },
  {
    "segmentnr":"BO_T02_D1603:126b-6",
    "original":"'o mtsho yid 'ong zla ba'i 'od byed ma \/\/",
    "folio":"126b",
    "stemmed":"mang mtsho yid ng zla ba d byed ma "
  },
  {
    "segmentnr":"BO_T02_D1603:126b-7",
    "original":"'gyur med bde bas rnam sgeg lha mo yi \/\/",
    "folio":"126b",
    "stemmed":"gyur med bde ba rnam sgeg lha mo yi "
  },
  {
    "segmentnr":"BO_T02_D1603:126b-8",
    "original":"lhun grub dpal gyis bdag la skyong gyur cig \/ lha dang lha min gtsug gi nor bu yi \/\/",
    "folio":"126b",
    "stemmed":"lhun grub dpal gyis bdag la skyong gyur cig lha dang lha min gtsug gi nor bu yi "
  },
  {
    "segmentnr":"BO_T02_D1603:126b-9",
    "original":"'od zer tshogs rnams bstar ba'i phreng ba yis \/\/",
    "folio":"126b",
    "stemmed":"d zer tshogs rnams bstar ba phreng ba yis "
  },
  {
    "segmentnr":"BO_T02_D1603:126b-10",
    "original":"khyod zhabs chu skyes la ni nyer mchod pa'i \/\/",
    "folio":"126b",
    "stemmed":"khyod zhabs chu skye la ni nyer mchod ba "
  },
  {
    "segmentnr":"BO_T02_D1603:126b-11",
    "original":"dbang phyug mdzes mas bka' drin rab tu stsol \/\/",
    "folio":"126b",
    "stemmed":"dbang phyug mdzes mas bka drin rab tu stsol "
  },
  {
    "segmentnr":"BO_T02_D1603:126b-12",
    "original":"'jig rten gsum gyi dbang phyug rab stsol bas \/\/",
    "folio":"126b",
    "stemmed":"jig rten gsum gyi dbang phyug rab stsol ba "
  },
  {
    "segmentnr":"BO_T02_D1603:126b-13",
    "original":"mchog tu gsal bar gar mdzad zhabs sen ni \/\/",
    "folio":"126b",
    "stemmed":"mchog tu gsal ba gar mdzad zhabs sen ni "
  },
  {
    "segmentnr":"BO_T02_D1603:126b-14",
    "original":"'jam mnyen sor mo la mdzes rtag pa ru \/\/",
    "folio":"126b",
    "stemmed":"jam mnyen sor mo la mdzes rtag ba ru "
  },
  {
    "segmentnr":"BO_T02_D1603:126b-15",
    "original":"dgyes pas bdag gi spyi por gzhag tu gsol \/\/",
    "folio":"126b",
    "stemmed":"dgyes ba bdag gi spyi por jog tu gsol "
  },
  {
    "segmentnr":"BO_T02_D1603:126b-16",
    "original":"rab gsal dri med dkyus ring spyan dag dang \/\/ snyan cha phyogs su 'khrol zhing 'dzum zhal can \/\/",
    "folio":"126b",
    "stemmed":"rab gsal dri med dkyu ring spyan dag dang snyan cha phyogs su khrol zhing dzum zhal can "
  },
  {
    "segmentnr":"BO_T02_D1603:126b-17",
    "original":"chu skyes dmar po'i mdangs gsal yum gyi gdong \/\/",
    "folio":"126b",
    "stemmed":"chu skye dmar po mdangs gsal yum gyi gdong "
  },
  {
    "segmentnr":"BO_T02_D1603:126b-18",
    "original":"bdag gi mig la mngon sum mthong ba stsol \/\/",
    "folio":"126b",
    "stemmed":"bdag gi mig la mngon sum mthong ba stsol "
  },
  {
    "segmentnr":"BO_T02_D1603:126b-19",
    "original":"bdud bzhi'i khrag gis yongs gang ka p'a la \/\/",
    "folio":"126b",
    "stemmed":"bdud bzhi khrag gis yongs gang ka pa la "
  },
  {
    "segmentnr":"BO_T02_D1603:126b-20",
    "original":"rab dkar phyag g-yon padma la chags pa \/\/",
    "folio":"126b",
    "stemmed":"rab dkar phyag g-yon padma la chags ba "
  },
  {
    "segmentnr":"BO_T02_D1603:126b-21",
    "original":"yongs rdzogs nyi ma'i dkyil 'khor gnyis kyi dbus \/\/",
    "folio":"126b",
    "stemmed":"yongs rdzogs nyi ma dkyil khor gnyis kyi dbus "
  },
  {
    "segmentnr":"BO_T02_D1603:126b-22",
    "original":"zla ba gzhon nu zhugs pa lta bur mdzes \/\/",
    "folio":"126b",
    "stemmed":"zla ba gzhon nu jug ba lta bur mdzes "
  },
  {
    "segmentnr":"BO_T02_D1603:126b-23",
    "original":"lha rnams la ni khyed cag thogs med kyi \/\/",
    "folio":"126b",
    "stemmed":"lha rnams la ni khyed cag thogs med kyi "
  },
  {
    "segmentnr":"BO_T02_D1603:126b-24",
    "original":"blo ngan rnam par 'joms zhes dbugs dbyung phyir \/\/",
    "folio":"126b",
    "stemmed":"blo ngan rnam ba joms zhes dbugs byin phyir "
  },
  {
    "segmentnr":"BO_T02_D1603:126b-25",
    "original":"g-yas pas phyar ba'i gri gug gyen phyags par \/\/",
    "folio":"126b",
    "stemmed":"g-yas ba phyar ba gri gug gyen phyags ba "
  },
  {
    "segmentnr":"BO_T02_D1603:126b-26",
    "original":"'dzin mkhas khyod ni 'gro ba'i ma ma'o \/\/",
    "folio":"126b",
    "stemmed":"dzin mkhas khyod ni gro ba ma ma "
  },
  {
    "segmentnr":"BO_T02_D1603:126b-27",
    "original":"rab dmar byi ru'i phung po mngon mtho ba \/\/",
    "folio":"126b",
    "stemmed":"rab dmar byi ru phung po mngon mtho ba "
  },
  {
    "segmentnr":"BO_T02_D1603:126b-28",
    "original":"mu tig phreng bas yongs su dkris pa bzhin \/\/",
    "folio":"126b",
    "stemmed":"mu tig phreng ba yongs su dkri ba bzhin "
  },
  {
    "segmentnr":"BO_T02_D1603:126b-29",
    "original":"phyag rgya lnga yis sku la rab brgyan cing \/\/",
    "folio":"126b",
    "stemmed":"phyag rgya lnga yis sku la rab rgyan cing "
  },
  {
    "segmentnr":"BO_T02_D1603:126b-30",
    "original":"nu 'bur rgyas pa do shal 'od kyis mdzes \/\/",
    "folio":"126b",
    "stemmed":"nu bur rgya ba do shal d kyis mdzes "
  },
  {
    "segmentnr":"BO_T02_D1603:126b-31",
    "original":"kun du 'gro ba'i sdig pa mun pa'i dpung \/\/",
    "folio":"126b",
    "stemmed":"kun du gro ba sdig ba mun ba dpung "
  },
  {
    "segmentnr":"BO_T02_D1603:126b-32",
    "original":"'joms shing 'phro bas phyogs bcu kun khyab pa'i \/\/",
    "folio":"126b",
    "stemmed":"joms shing phro ba phyogs chu kun khyab ba "
  },
  {
    "segmentnr":"BO_T02_D1603:127a-0",
    "original":"'od @127a * \/\/",
    "folio":"127a",
    "stemmed":"d "
  },
  {
    "segmentnr":"BO_T02_D1603:127a-1",
    "original":"zer tshogs rnams khyod kyis yangs 'dzin pa \/\/",
    "folio":"127a",
    "stemmed":"zer tshogs rnams khyod kyis yangs dzin ba "
  },
  {
    "segmentnr":"BO_T02_D1603:127a-2",
    "original":"ma lus 'gro ba bsgral ba'i ched du lags \/\/",
    "folio":"127a",
    "stemmed":"ma lus gro ba bsgral ba ched du lags "
  },
  {
    "segmentnr":"BO_T02_D1603:127a-3",
    "original":"gru mo'i kha tv'am rtser son thod pa ni \/\/",
    "folio":"127a",
    "stemmed":"gru mo kha tv rtser son thod ba ni "
  },
  {
    "segmentnr":"BO_T02_D1603:127a-4",
    "original":"'ching grol bral las rdo rje'i gdan thob ces \/\/",
    "folio":"127a",
    "stemmed":"ching grol bral las rdo rje gdan thob ces "
  },
  {
    "segmentnr":"BO_T02_D1603:127a-5",
    "original":"phreng bar brgyus pa'i mgo rnams dbugs btang nas \/\/",
    "folio":"127a",
    "stemmed":"phreng ba rgyud ba mgo rnams dbugs gtong nas "
  },
  {
    "segmentnr":"BO_T02_D1603:127a-6",
    "original":"lha mor 'khyud pas do shal byas pa bzhin ;",
    "folio":"127a",
    "stemmed":"lha mor khyud ba do shal byed ba bzhin "
  },
  {
    "segmentnr":"BO_T02_D1603:127a-7",
    "original":"\/ gan rkyal bsgyel ba'i mo ro zhabs 'og na \/\/",
    "folio":"127a",
    "stemmed":"gan rkyal sgyel ba mo ro zhabs g na "
  },
  {
    "segmentnr":"BO_T02_D1603:127a-8",
    "original":"khyod la gyen du phyogs par blta ba ni \/\/",
    "folio":"127a",
    "stemmed":"khyod la gyen du phyogs ba lta ba ni "
  },
  {
    "segmentnr":"BO_T02_D1603:127a-9",
    "original":"skyabs gzhan bral ba bdag la'ang khyod kyi 'od \/\/",
    "folio":"127a",
    "stemmed":"skyob gzhan bral ba bdag la khyod kyi d "
  },
  {
    "segmentnr":"BO_T02_D1603:127a-10",
    "original":"bdag lta'i mgon du gyur zhes gnas la nyal \/\/",
    "folio":"127a",
    "stemmed":"bdag lta mgon du gyur zhes gnas la nyal "
  },
  {
    "segmentnr":"BO_T02_D1603:127a-11",
    "original":"me tog chun po rnams ni char gnag pa'i \/\/",
    "folio":"127a",
    "stemmed":"me tog chun po rnams ni char gnag ba "
  },
  {
    "segmentnr":"BO_T02_D1603:127a-12",
    "original":"dbu skra sil bur 'phyang la ji ltar btags \/\/",
    "folio":"127a",
    "stemmed":"dbu skra sil bur phyang la ji ltar dogs "
  },
  {
    "segmentnr":"BO_T02_D1603:127a-13",
    "original":"ngo tsha mchog dang sna tshogs dar 'phyang na \/\/",
    "folio":"127a",
    "stemmed":"ngo tsha mchog dang sna tshogs dar phyang na "
  },
  {
    "segmentnr":"BO_T02_D1603:127a-14",
    "original":"gcer bu'i cha lugs dag gis bsnyems pa ci \/\/",
    "folio":"127a",
    "stemmed":"bcer bu cha lugs dag gis snyems ba ci "
  },
  {
    "segmentnr":"BO_T02_D1603:127a-15",
    "original":"rnam mang rin chen tshogs kyis bkra ba yi \/\/",
    "folio":"127a",
    "stemmed":"rnam mang rin chen tshogs kyis bkra ba yi "
  },
  {
    "segmentnr":"BO_T02_D1603:127a-16",
    "original":"mdangs ldan gser gyi rgyan cha spangs nas khyod \/\/",
    "folio":"127a",
    "stemmed":"mdangs ldan gser gyi rgyan cha spong nas khyod "
  },
  {
    "segmentnr":"BO_T02_D1603:127a-17",
    "original":"rgyan mchog mi yi rus pa la bzhed na \/\/",
    "folio":"127a",
    "stemmed":"rgyan mchog mi yi rus ba la bzhed na "
  },
  {
    "segmentnr":"BO_T02_D1603:127a-18",
    "original":"dgyes phyir rin chen 'bul na ji ltar 'gyur \/\/",
    "folio":"127a",
    "stemmed":"dgyes phyir rin chen bul na ji ltar gyur "
  },
  {
    "segmentnr":"BO_T02_D1603:127a-19",
    "original":"khyod zhal mngon par yid 'od gyur na ko \/\/",
    "folio":"127a",
    "stemmed":"khyod zhal mngon ba yid d gyur na ko "
  },
  {
    "segmentnr":"BO_T02_D1603:127a-20",
    "original":"rab khros phag zhal g-yas su sngon 'di gang \/\/",
    "folio":"127a",
    "stemmed":"rab khro phag zhal g-yas su sngon di gang "
  },
  {
    "segmentnr":"BO_T02_D1603:127a-21",
    "original":"khyod sku rnam par sgeg pa'i tshul 'dzin na \/\/",
    "folio":"127a",
    "stemmed":"khyod sku rnam ba sgeg ba tshul dzin na "
  },
  {
    "segmentnr":"BO_T02_D1603:127a-22",
    "original":"gcer bu ngo tsha bral 'dra 'di ci zhig \/ khyod kyi spyod tshul 'jig rten las 'das shing \/\/",
    "folio":"127a",
    "stemmed":"bcer bu ngo tsha bral dra di ci jig khyod kyi spyod tshul jig rten las da shing "
  },
  {
    "segmentnr":"BO_T02_D1603:127a-23",
    "original":"rnam lnga'i dbang po bde bas brgyal de'i phyir \/\/",
    "folio":"127a",
    "stemmed":"rnam lnga dbang po bde ba brgyal de phyir "
  },
  {
    "segmentnr":"BO_T02_D1603:127a-24",
    "original":"bstod par gyur kyang khyod kyis gsan ma lags \/\/",
    "folio":"127a",
    "stemmed":"bstod ba gyur kyang khyod kyis gsan ma lags "
  },
  {
    "segmentnr":"BO_T02_D1603:127a-25",
    "original":"de slang bdag gi bstod tshul ci 'drar 'gyur \/\/",
    "folio":"127a",
    "stemmed":"de slang bdag gi bstod tshul ci drar gyur "
  },
  {
    "segmentnr":"BO_T02_D1603:127a-26",
    "original":"thog med ma rig mun pa btsal ba yi \/\/",
    "folio":"127a",
    "stemmed":"thogs med ma rig mun ba btsal ba yi "
  },
  {
    "segmentnr":"BO_T02_D1603:127a-27",
    "original":"sgron ma g-yo med rab tu sbar ba'i phyir \/\/",
    "folio":"127a",
    "stemmed":"sgron ma g-yo med rab tu sbor ba phyir "
  },
  {
    "segmentnr":"BO_T02_D1603:127a-28",
    "original":"bsam gyis mi khyab gzugs can gsang ba yi \/\/",
    "folio":"127a",
    "stemmed":"bsam gyis mi khyab gzugs can gsang ba yi "
  },
  {
    "segmentnr":"BO_T02_D1603:127a-29",
    "original":"chos 'byung snying po'i ze 'brur gnas pa khyod \/\/",
    "folio":"127a",
    "stemmed":"chos byung snying po ze brur gnas ba khyod "
  },
  {
    "segmentnr":"BO_T02_D1603:127a-30",
    "original":"rdo rje chu skyes spyong ba'i las kyis ni \/\/",
    "folio":"127a",
    "stemmed":"rdo rje chu skye spyong ba las kyis ni "
  },
  {
    "segmentnr":"BO_T02_D1603:127a-31",
    "original":"rang gnas las spyod lhun po'i khyim dag tu \/\/",
    "folio":"127a",
    "stemmed":"rang gnas las spyod lhun po khyim dag tu "
  },
  {
    "segmentnr":"BO_T02_D1603:127a-32",
    "original":"rtsol med 'bar ba'i glog gis 'khor lo gsum \/\/",
    "folio":"127a",
    "stemmed":"rtsol med bar ba glog gis khor lo gsum "
  },
  {
    "segmentnr":"BO_T02_D1603:127a-33",
    "original":"bcom las rnam rtog klong 'khor tshogs zhi ma \/\/",
    "folio":"127a",
    "stemmed":"joms las rnam rtogs klong khor tshogs zhi ma "
  },
  {
    "segmentnr":"BO_T02_D1603:127a-34",
    "original":"'dod ma khyod kyi spyan sngar bkod pa yi \/\/",
    "folio":"127a",
    "stemmed":"dod ma khyod kyi spyan sngar bkod ba yi "
  },
  {
    "segmentnr":"BO_T02_D1603:127a-35",
    "original":"mchod pa'i rgyan la mi gzigs rol mo'i sgra \/\/",
    "folio":"127a",
    "stemmed":"mchod ba rgyan la mi gzigs rol mo sgra "
  },
  {
    "segmentnr":"BO_T02_D1603:127a-36",
    "original":"mi gsan dri bzang mi snom bdud rtsi'i bcud \/\/",
    "folio":"127a",
    "stemmed":"mi gsan dri bzang mi snom bdud rtsi bcud "
  },
  {
    "segmentnr":"BO_T02_D1603:127a-37",
    "original":"myang dang reg la'ang reg mi mdzad aa ye \/\/",
    "folio":"127a",
    "stemmed":"myang dang reg la reg mi mdzad aa ye "
  },
  {
    "segmentnr":"BO_T02_D1603:127a-38",
    "original":"de ni rang gi rje btsun nyid la khyod \/\/",
    "folio":"127a",
    "stemmed":"de ni rang gi rje btsun nyid la khyod "
  },
  {
    "segmentnr":"BO_T02_D1603:127a-39",
    "original":"rjes su chags pa'i gzhan dbang gyur las te \/\/",
    "folio":"127a",
    "stemmed":"rjes su chags ba gzhan dbang gyur las te "
  },
  {
    "segmentnr":"BO_T02_D1603:127a-40",
    "original":"de phyir khyod bsgoms pa las stong pa nyid \/\/",
    "folio":"127a",
    "stemmed":"de phyir khyod sgom ba las stong ba nyid "
  },
  {
    "segmentnr":"BO_T02_D1603:127a-41",
    "original":"'bras gyur bdag gi skye ba 'bras bur bcas \/\/",
    "folio":"127a",
    "stemmed":"bras gyur bdag gi skye ba bras bur cha "
  },
  {
    "segmentnr":"BO_T02_D1603:127a-42",
    "original":"lhun po'i rtser son padma'i snal ma ltar \/\/",
    "folio":"127a",
    "stemmed":"lhun po rtser son padma snal ma ltar "
  },
  {
    "segmentnr":"BO_T02_D1603:127a-43",
    "original":"phra ba'i sku yi 'od zer dus mtha'i mes \/\/",
    "folio":"127a",
    "stemmed":"phra ba sku yi d zer dus mtha mes "
  },
  {
    "segmentnr":"BO_T02_D1603:127b-0",
    "original":"@127b kun du bzang po 'jug pa'i nags bsregs nas \/\/",
    "folio":"127b",
    "stemmed":"kun du bzang po jug ba nags bsregs nas "
  },
  {
    "segmentnr":"BO_T02_D1603:127b-1",
    "original":"ri dbang po la mngon par phebs bzhin gnas \/\/",
    "folio":"127b",
    "stemmed":"ri dbang po la mngon ba phebs bzhin gnas "
  },
  {
    "segmentnr":"BO_T02_D1603:127b-2",
    "original":"rab 'bar rtse mo can gyis rgyu skar gyi \/\/",
    "folio":"127b",
    "stemmed":"rab bar rtse mo can gyis rgyu skar gyi "
  },
  {
    "segmentnr":"BO_T02_D1603:127b-3",
    "original":"bdag po bzhu ba las bab bdud rtsi'i char \/\/",
    "folio":"127b",
    "stemmed":"bdag po ju ba las bab bdud rtsi char "
  },
  {
    "segmentnr":"BO_T02_D1603:127b-4",
    "original":"blugs gtor rgyun gyis rnam rtog bag chags bcas \/\/",
    "folio":"127b",
    "stemmed":"blugs thor rgyun gyis rnam rtogs bag chags cha "
  },
  {
    "segmentnr":"BO_T02_D1603:127b-5",
    "original":"ring dor bde chen zab mo'i rgya mtsho thim \/\/",
    "folio":"127b",
    "stemmed":"ring dor bde chen zab mo rgya mtsho thim "
  },
  {
    "segmentnr":"BO_T02_D1603:127b-6",
    "original":"dmigs med thugs rje can khyod yid bzhin gyi \/\/",
    "folio":"127b",
    "stemmed":"dmigs med thugs rje can khyod yid bzhin gyi "
  },
  {
    "segmentnr":"BO_T02_D1603:127b-7",
    "original":"nor bu dpag bsam shing ltar ri dbang las \/\/",
    "folio":"127b",
    "stemmed":"nor bu dpog bsam shing ltar ri dbang las "
  },
  {
    "segmentnr":"BO_T02_D1603:127b-8",
    "original":"lus can kun la rtag tu 'bad med par \/\/",
    "folio":"127b",
    "stemmed":"lus can kun la rtag tu bad med ba "
  },
  {
    "segmentnr":"BO_T02_D1603:127b-9",
    "original":"dga' dang dpal dang rtag bde sbyin par mdzad \/\/",
    "folio":"127b",
    "stemmed":"dga dang dpal dang rtag bde sbyin ba mdzad "
  },
  {
    "segmentnr":"BO_T02_D1603:127b-10",
    "original":"skye 'jig dang bral chung du chen po dang \/\/ phyin ci log 'das shes rab thabs dag las \/\/",
    "folio":"127b",
    "stemmed":"skye jig dang bral chung du chen po dang phyin ci log da shes rab thabs dag las "
  },
  {
    "segmentnr":"BO_T02_D1603:127b-11",
    "original":"rtag tu dga' ba dam pa rab 'bar bas \/\/",
    "folio":"127b",
    "stemmed":"rtag tu dga ba dam ba rab bar ba "
  },
  {
    "segmentnr":"BO_T02_D1603:127b-12",
    "original":"bdag gi nyon mongs shes bya'i sgrib pa choms \/\/",
    "folio":"127b",
    "stemmed":"bdag gi nyon mongs shes byed sgrib ba choms "
  },
  {
    "segmentnr":"BO_T02_D1603:127b-13",
    "original":"rnam rnams gya gyu'i ngang tshul sdem po can \/\/",
    "folio":"127b",
    "stemmed":"rnam rnams gyas gyu ngang tshul sdem po can "
  },
  {
    "segmentnr":"BO_T02_D1603:127b-14",
    "original":"tshom rkun lta bur rnam pa mang po'i don \/\/",
    "folio":"127b",
    "stemmed":"tshom rkun lta bur rnam ba mang po don "
  },
  {
    "segmentnr":"BO_T02_D1603:127b-15",
    "original":"nye bar len cing yul rnams za byed pa \/\/",
    "folio":"127b",
    "stemmed":"nye ba len cing yul rnams za byed ba "
  },
  {
    "segmentnr":"BO_T02_D1603:127b-16",
    "original":"de phyir sems la ci slad smod mi bgyid \/\/",
    "folio":"127b",
    "stemmed":"de phyir sems la ci slad smod mi bgyid "
  },
  {
    "segmentnr":"BO_T02_D1603:127b-17",
    "original":"'on kyang 'gro spyod kun spangs stong nyid kyi \/\/",
    "folio":"127b",
    "stemmed":"n kyang gro spyod kun spong stong nyid kyi "
  },
  {
    "segmentnr":"BO_T02_D1603:127b-18",
    "original":"khyim du ci dgar zhugs la bde ba che'o \/\/",
    "folio":"127b",
    "stemmed":"khyim du ci dgar jug la bde ba che "
  },
  {
    "segmentnr":"BO_T02_D1603:127b-19",
    "original":"mchog gi rol khyod ni rol gyur pa \/\/",
    "folio":"127b",
    "stemmed":"mchog gi rol khyod ni rol gyur ba "
  },
  {
    "segmentnr":"BO_T02_D1603:127b-20",
    "original":"ae ma'o sems 'di'i nyer len ma lags sam \/\/",
    "folio":"127b",
    "stemmed":"ae ma sems di nyer len ma lags sam "
  },
  {
    "segmentnr":"BO_T02_D1603:127b-21",
    "original":"gang tshe steng du song bas rnam gsum gyi \/\/",
    "folio":"127b",
    "stemmed":"gang tshe steng du gro ba rnam gsum gyi "
  },
  {
    "segmentnr":"BO_T02_D1603:127b-22",
    "original":"'khor lo kun bsregs bde ba chen po ni \/\/",
    "folio":"127b",
    "stemmed":"khor lo kun bsregs bde ba chen po ni "
  },
  {
    "segmentnr":"BO_T02_D1603:127b-23",
    "original":"bzhu zhing bkug las spros pa med pa yi \/\/",
    "folio":"127b",
    "stemmed":"ju zhing gugs las spros ba med ba yi "
  },
  {
    "segmentnr":"BO_T02_D1603:127b-24",
    "original":"lha mo rang gi gnas su yongs su zhugs \/\/",
    "folio":"127b",
    "stemmed":"lha mo rang gi gnas su yongs su jug "
  },
  {
    "segmentnr":"BO_T02_D1603:127b-25",
    "original":"de tshe rlung 'di'i rgyu ba gang du byed \/\/",
    "folio":"127b",
    "stemmed":"de tshe rlung di rgyu ba gang du byed "
  },
  {
    "segmentnr":"BO_T02_D1603:127b-26",
    "original":"dbang po phyin ci log pa'ang gang du 'gyur \/\/",
    "folio":"127b",
    "stemmed":"dbang po phyin ci log ba gang du gyur "
  },
  {
    "segmentnr":"BO_T02_D1603:127b-27",
    "original":"kun nas gya gyu'i sems ni gang du g-yo \/\/",
    "folio":"127b",
    "stemmed":"kun nas gyas gyu sems ni gang du g-yo "
  },
  {
    "segmentnr":"BO_T02_D1603:127b-28",
    "original":"yul la longs spyod tshul kyang gang du 'gyur \/\/",
    "folio":"127b",
    "stemmed":"yul la longs spyod tshul kyang gang du gyur "
  },
  {
    "segmentnr":"BO_T02_D1603:127b-29",
    "original":"bgo ba dang bral mi rus rgyan du byas \/\/",
    "folio":"127b",
    "stemmed":"bgod ba dang bral mi rus rgyan du byed "
  },
  {
    "segmentnr":"BO_T02_D1603:127b-30",
    "original":"rol gnas shing thod pa'i snod 'chang ba \/\/",
    "folio":"127b",
    "stemmed":"rol gnas shing thod ba snod chang ba "
  },
  {
    "segmentnr":"BO_T02_D1603:127b-31",
    "original":"dngos po bral bas stong par zhugs de'i phyir \/\/",
    "folio":"127b",
    "stemmed":"dngos po bral ba stong ba jug de phyir "
  },
  {
    "segmentnr":"BO_T02_D1603:127b-32",
    "original":"mi 'chi las gzhan khyod la dngos ci blang \/\/",
    "folio":"127b",
    "stemmed":"mi chi las gzhan khyod la dngos ci blang "
  },
  {
    "segmentnr":"BO_T02_D1603:127b-33",
    "original":"'on tang 'gro kun rga shi'i 'jigs pa ni \/\/",
    "folio":"127b",
    "stemmed":"n tang gro kun rga chi jigs ba ni "
  },
  {
    "segmentnr":"BO_T02_D1603:127b-34",
    "original":"'joms shing skyong ba'i dam bca' bsnyems ma kye \/\/",
    "folio":"127b",
    "stemmed":"joms shing skyong ba dam chos snyems ma kye "
  },
  {
    "segmentnr":"BO_T02_D1603:127b-35",
    "original":"bdag kyang rnal 'byor che la shes rab thabs \/\/",
    "folio":"127b",
    "stemmed":"bdag kyang rnal byor che la shes rab thabs "
  },
  {
    "segmentnr":"BO_T02_D1603:127b-36",
    "original":"brtan las phyag rgya chen po'i dngos grub stsol \/\/",
    "folio":"127b",
    "stemmed":"brtan las phyag rgya chen po dngos grub stsol "
  },
  {
    "segmentnr":"BO_T02_D1603:127b-37",
    "original":"khyod la dad pas bstod par rab brtson pa \/\/",
    "folio":"127b",
    "stemmed":"khyod la dad ba bstod ba rab brtson ba "
  },
  {
    "segmentnr":"BO_T02_D1603:127b-38",
    "original":"blo dman bdag gi nongs sam nyes med sring \/\/",
    "folio":"127b",
    "stemmed":"blo dman bdag gi nongs sam nyes med sring "
  },
  {
    "segmentnr":"BO_T02_D1603:127b-39",
    "original":"gang phyir khyod nyid 'gro ba'i mgon gyur slad \/\/",
    "folio":"127b",
    "stemmed":"gang phyir khyod nyid gro ba mgon gyur slad "
  },
  {
    "segmentnr":"BO_T02_D1603:127b-40",
    "original":"nongs na'ang mchog gi ma mas bzod par rigs \/\/",
    "folio":"127b",
    "stemmed":"nongs na mchog gi ma mas bzod ba rigs "
  },
  {
    "segmentnr":"BO_T02_D1603:127b-41",
    "original":"khyod la bstod pa'i dge ba dri med gang zhig ni \/\/",
    "folio":"127b",
    "stemmed":"khyod la bstod ba dge ba dri med gang jig ni "
  },
  {
    "segmentnr":"BO_T02_D1603:127b-42",
    "original":"bdag gis thob pa de yis srog chags phung po rnams \/\/",
    "folio":"127b",
    "stemmed":"bdag gis thob ba de yis srog chags phung po rnams "
  },
  {
    "segmentnr":"BO_T02_D1603:128a-0",
    "original":"@128a * \/\/ mi dman rab dga'i dga' bas rtag tu snying gtams nas \/\/",
    "folio":"128a",
    "stemmed":"mi dman rab dga dga ba rtag tu snying gtams nas "
  },
  {
    "segmentnr":"BO_T02_D1603:128a-1",
    "original":"phyag rgya chen po'i dngos grub dam pa rnyed gyur cig \/ rdo rje phag mo'i bstod pa rim pa gnyis pa zhes bya ba \/",
    "folio":"128a",
    "stemmed":"phyag rgya chen po dngos grub dam ba rnyed gyur cig rdo rje phag mo bstod ba rim ba gnyis ba zhes byed ba "
  },
  {
    "segmentnr":"BO_T02_D1603:128a-2",
    "original":"rdo rje btsun mo 'di nyid kyis mngon sum du byin gyis brlabs pa'i grub pa'i dbang phyug \/ rgya gar shar phyogs kyi pandi ta chen po shr'i ba na ratna'i zhal snga nas kyis mdzad pa rdzogs so \/",
    "folio":"128a",
    "stemmed":"rdo rje btsun mo di nyid kyis mngon sum du byin gyis brlabs ba grub ba dbang phyug rgya gar char phyogs kyi pandi ta chen po shr ba na ratna zhal snga nas kyis mdzad ba rdzogs so "
  },
  {
    "segmentnr":"BO_T02_D1603:128a-3",
    "original":"\/\/ \/ pandi ta chen po de nyid dang \/ chos 'khor lo ts'a ba 'jam dpal ye shes kyis 'bras yul nor bu'i gling du bsgyur ba las \/",
    "folio":"128a",
    "stemmed":"pandi ta chen po de nyid dang chos khor lo tsa ba jam dpal ye shes kyis bras yul nor bu gling du sgyur ba las "
  },
  {
    "segmentnr":"BO_T02_D1603:128a-4",
    "original":"phyis mi 'phrogs pa'i mkhyen pa dang dad pa rnam par dkar ba'i lugs gnyis kyi dbang phyug dam pa aa mo gha siddhi sa bkas gnang ba las \/",
    "folio":"128a",
    "stemmed":"byid mi phrogs ba mkhyen ba dang dad ba rnam ba dkar ba lugs gnyis kyi dbang phyug dam ba aa mo gha siddhi sa gas gnang ba las "
  },
  {
    "segmentnr":"BO_T02_D1603:128a-5",
    "original":"pandi ta chen po de nyid kyi bka' drin gyis 'tsho ba'i dge slong chos smra ba rgya mtsho'i sde zhes bya bas mi bcos su mi rung ba rnams bcos shing don la rton pa nyid du gtan la phab pa 'di ni \/",
    "folio":"128a",
    "stemmed":"pandi ta chen po de nyid kyi bka drin gyis tsho ba dge slong chos smra ba rgya mtsho sde zhes byed ba mi chos su mi rung ba rnams chos shing don la rton ba nyid du gtan la bebs ba di ni "
  },
  {
    "segmentnr":"BO_T02_D1603:128a-6",
    "original":"lho phyogs kyi ri bo'i rgyud rin po che'i gling skal bzang dga' ba'i tshal zhes bya ba'i mdun sa dam par grub par bgyis pa shu bha ma stu sarba dza ga tam\/\/",
    "folio":"128a",
    "stemmed":"lho phyogs kyi ri bo brgyud rin po che gling skal bzang dga ba tshal zhes byed ba mdun sa dam ba grub ba bgyid ba shu bha ma stu sarba dza ga "
  }
]